orex/__init__.py
orex/backend.py
orex/collection.py
orex/match.py
orex/patterns.py
orex/stringify.py
orex-0.0.2.dist-info/WHEEL
orex-0.0.2.dist-info/METADATA
orex-0.0.2.dist-info/RECORD
